probstructs.cp37-win_amd64.pyd
probstructs-0.2.8.dist-info/LICENSE
probstructs-0.2.8.dist-info/METADATA
probstructs-0.2.8.dist-info/WHEEL
probstructs-0.2.8.dist-info/top_level.txt
probstructs-0.2.8.dist-info/RECORD
